Utils/__init__.py
Utils/all_utils.py
oneNeuron/__init__.py
oneNeuron/perceptron.py
oneNeuron_pypi_ManimozhiSathish-0.0.3.dist-info/LICENSE
oneNeuron_pypi_ManimozhiSathish-0.0.3.dist-info/METADATA
oneNeuron_pypi_ManimozhiSathish-0.0.3.dist-info/WHEEL
oneNeuron_pypi_ManimozhiSathish-0.0.3.dist-info/top_level.txt
oneNeuron_pypi_ManimozhiSathish-0.0.3.dist-info/RECORD
