Metadata-Version: 2.1
Name: oneNeuron-pypi-ManimozhiSathish
Version: 0.0.3
Summary: It's an implementation of perceptron
Home-page: https://github.com/{USER_NAME}/{PROJECT_NAME}
Author: ManimozhiSathish
Author-email: mozhi7482@gmail.com
License: UNKNOWN
Project-URL: Bug Tracker, https://github.com/ManimozhiSathish/oneNeuron_pypi/issues
Platform: UNKNOWN
Classifier: Programming Language :: Python :: 3
Classifier: License :: OSI Approved :: MIT License
Classifier: Operating System :: OS Independent
Requires-Python: >=3.7
License-File: LICENSE
Requires-Dist: numpy
Requires-Dist: tqdm
